pylightpanda/__init__.py
pylightpanda/core.py
pylightpanda/bin/lightpanda
pylightpanda-0.1.1.dist-info/METADATA
pylightpanda-0.1.1.dist-info/WHEEL
pylightpanda-0.1.1.dist-info/top_level.txt
pylightpanda-0.1.1.dist-info/RECORD
