Metadata-Version: 2.1
Name: Pylightpanda
Version: 0.1.1
Summary: A Python package wrapping the lightpanda binary to fetch HTML content.
Author-email: ruprof <ruprof.info@gmail.com>
License: MIT License
Project-URL: Homepage, https://github.com/ruprof/pylightpanda
Project-URL: Repository, https://github.com/ruprof/pylightpanda.git
Requires-Python: >=3.6
